torrequests
