Metadata-Version: 1.1
Name: torrequests
Version: 1.1.10
Summary: Wrapper for requests over Tor
Home-page: https://github.com/di3g0bs0n/torrequests
Author: Diego Fernandez
Author-email: di3g0bs0n@gmail.com
License: GPLv3
Keywords: tor requests
Platform: UNKNOWN
Classifier: Development Status :: 5 - Production/Stable
Classifier: License :: OSI Approved :: GNU General Public License v3 (GPLv3)
Classifier: Programming Language :: Python :: 2.7
Classifier: Topic :: Utilities
